README.md
setup.cfg
setup.py
autokeras_tabular/__init__.py
autokeras_tabular.egg-info/PKG-INFO
autokeras_tabular.egg-info/SOURCES.txt
autokeras_tabular.egg-info/dependency_links.txt
autokeras_tabular.egg-info/requires.txt
autokeras_tabular.egg-info/top_level.txt
autokeras_tabular/examples/__init__.py
autokeras_tabular/examples/task_modules/__init__.py
autokeras_tabular/examples/task_modules/tabular/__init__.py
autokeras_tabular/examples/task_modules/tabular/tabular_classification_binary.py
autokeras_tabular/examples/task_modules/tabular/tabular_classification_multiclass.py
autokeras_tabular/examples/task_modules/tabular/tabular_regression.py
autokeras_tabular/tabular/__init__.py
autokeras_tabular/tabular/tabular_preprocessor.py
autokeras_tabular/tabular/tabular_supervised.py
tests/tabular/__init__.py
tests/tabular/test_tabular_preprocessor.py
tests/tabular/test_tabular_supervised.py